<?xml version="1.0" encoding="UTF-8"?>
<diagram-index>
    <folder name="思维导图" id="/.root">
        <diagram name="p2p" id="6049AC43271381B76326A558"></diagram>
        <diagram name="Overview of consensus protocols" id="3AC0F3CB2A70BFBE5927B7E2"></diagram>
        <diagram name="Lecture2 berkeley" id="570AAED03B1FC5865E0816AE"></diagram>
        <diagram name="lecture3" id="7E1D69393EE26F037C020F76"></diagram>
        <diagram name="how is Clique design here" id="163DDABC5DBC145B72BC561F"></diagram>
        <diagram name="scala设计原则" id="0B238EB31BEF03C81663AB48"></diagram>
        <diagram name="Bitcoin decentralization,lecture2" id="5B3BB50974FD0DA512407B2D"></diagram>
        <diagram name="Monoid" id="7AE4140C561D351B3893E900"></diagram>
        <diagram name="Implicit" id="60F76A0E7DF5CA9514D3B5D1"></diagram>
        <diagram name="IntSet :假设演绎法，三条基础" id="5B2E37DE782F2DC72C233505"></diagram>
        <diagram name="Monads, is a type" id="09383CBA4DF97EC3231E52B6"></diagram>
        <diagram name="美国著名商学院" id="48EACF4E0F92FF6A087AA5A4"></diagram>
        <diagram name="Clique" id="04509A7A3EB064382228CF6E"></diagram>
        <diagram name="lecture 1" id="230CEED5164F9B690D1FA8A7"></diagram>
        <diagram name="berkeley" id="6F4766A171D02D351CFAD8EA"></diagram>
        <diagram name="CS251" id="14DB24AA4118286F3EE78E6F"></diagram>
        <diagram name="营销" id="38236E866586741A1E855EE2"></diagram>
        <diagram name="欢迎" id="1C20071C521207740100136D"></diagram>
        <diagram name="Clique源码功能" id="6228DD190F2311EC1D2B5247"></diagram>
        <diagram name="hash function" id="4515B11B69AC7FB434E906E2"></diagram>
        <diagram name="programing languages" id="5A6326A4392C44A618089C06"></diagram>
        <diagram name="cs251" id="0AA1A2E34445AAB42E94D6F6"></diagram>
        <diagram name="scala" id="25BCF0C1771C09FF3E3F1FAC"></diagram>
        <diagram name="famous AM CS" id="1C0A5DE92F3C5FCC2994A4FC"></diagram>
        <diagram name="scala" id="07F5B61E6223D6574558ECF7"></diagram>
        <diagram name="中心主题" id="7D0C71A1313A5A93235CEADA"></diagram>
    </folder>
</diagram-index>